scidatalib/__init__.py
scidatalib/cli.py
scidatalib/io/__init__.py
scidatalib/io/formats.py
scidatalib/io/jcamp.py
scidatalib/io/rruff.py
scidatalib/scidata.py
scidatalib-0.4.1.dist-info/LICENSE.txt
scidatalib-0.4.1.dist-info/METADATA
scidatalib-0.4.1.dist-info/WHEEL
scidatalib-0.4.1.dist-info/entry_points.txt
scidatalib-0.4.1.dist-info/RECORD
