Metadata-Version: 2.3
Name: SciDataLib
Version: 0.4.1
Summary: Python library for development of SciData JSON-LD files
License: MIT
Keywords: scidata,scidatalib
Author: Stuart Chalk
Author-email: schalk@unf.edu
Requires-Python: >=3.10,<4.0
Classifier: License :: OSI Approved :: MIT License
Classifier: Operating System :: OS Independent
Classifier: Programming Language :: Python :: 3
Classifier: Programming Language :: Python :: 3.10
Classifier: Programming Language :: Python :: 3.11
Classifier: Programming Language :: Python :: 3.12
Classifier: Programming Language :: Python :: 3.13
Requires-Dist: numpy (>=2.2,<3.0)
Project-URL: Homepage, https://github.com/chalklab/SciDataLib
Project-URL: Repository, https://github.com/chalklab/SciDataLib
